pdm_python_project_template/__init__.py
pdm_python_project_template-0.1.6.dist-info/METADATA
pdm_python_project_template-0.1.6.dist-info/WHEEL
pdm_python_project_template-0.1.6.dist-info/RECORD
